Dataset.py
Highlighter.py
RedundancyManager.py
SentenceRanker.py
THExt/DatasetPlus.py
THExt/Highlighter.py
THExt/RedundancyManager.py
THExt/SentenceRankerPlus.py
THExt/__init__.py
thext/DatasetPlus.py
thext/Highlighter.py
thext/RedundancyManager.py
thext/SentenceRankerPlus.py
thext/__init__.py
thext-1.0.dist-info/LICENSE.txt
thext-1.0.dist-info/METADATA
thext-1.0.dist-info/WHEEL
thext-1.0.dist-info/top_level.txt
thext-1.0.dist-info/RECORD
