Metadata-Version: 2.1
Name: thext
Version: 1.0
Summary: THExt - Transformer-based Highlights Extraction
Home-page: https://github.com/MorenoLaQuatra/THExt
Author: Moreno La Quatra
Author-email: moreno.laquatra@gmail.com
License: UNKNOWN
Platform: UNKNOWN
Classifier: Programming Language :: Python :: 3
Classifier: License :: OSI Approved :: GNU General Public License v3 (GPLv3)
Classifier: Programming Language :: Python :: 3.8
Classifier: Programming Language :: Python :: 3.7
Classifier: Programming Language :: Python :: 3.6
Classifier: Operating System :: OS Independent
License-File: LICENSE.txt
Requires-Dist: nltk
Requires-Dist: spacy
Requires-Dist: mlxtend
Requires-Dist: numpy
Requires-Dist: sentence-transformers
Requires-Dist: torch
Requires-Dist: multiprocess
Requires-Dist: py-rouge
Requires-Dist: scispacy
Provides-Extra: dev
Requires-Dist: pytest (>=3.7) ; extra == 'dev'
